gttrl/__init__.py
gttrl/__main__.py
gttrl/cli.py
gttrl/constants.py
gttrl/enums.py
gttrl/launcher.py
gttrl/models.py
gttrl-1.4.dist-info/entry_points.txt
gttrl-1.4.dist-info/WHEEL
gttrl-1.4.dist-info/METADATA
gttrl-1.4.dist-info/RECORD
