Metadata-Version: 2.1
Name: gttrl
Version: 1.4
Summary: A cross-platform CLI launcher for Toontown Rewritten.
Author: glomatico
Requires-Python: >=3.8
Requires-Dist: click
Requires-Dist: requests
Requires-Dist: tqdm
Project-URL: homepage, https://github.com/glomatico/gttrl
Project-URL: repository, https://github.com/glomatico/gttrl
